cadastropessoaendereco_lib-0.1.2.dist-info/licenses/LICENSE
model/__init__.py
model/dto.py
model/models.py
repository/__init__.py
repository/base.py
service/__init__.py
service/base.py
test/__init__.py
test/test_models.py
test/tests.py
util/__init__.py
util/database.py
cadastropessoaendereco_lib-0.1.2.dist-info/METADATA
cadastropessoaendereco_lib-0.1.2.dist-info/WHEEL
cadastropessoaendereco_lib-0.1.2.dist-info/top_level.txt
cadastropessoaendereco_lib-0.1.2.dist-info/RECORD
