Metadata-Version: 2.4
Name: cadastroPessoaEndereco-Lib
Version: 0.1.2
Summary: Biblioteca que permite o cadastro de pessoas e endereços e gera um banco de dados.
Home-page: https://github.com/LucasMarianiG/PessoaEndereco-lib.git
Author: Lucas Mariani Gomes
Author-email: lucas2607.gomes@gmail.com
Classifier: Programming Language :: Python :: 3
Classifier: License :: OSI Approved :: MIT License
Classifier: Operating System :: OS Independent
Requires-Python: >=3.8
License-File: LICENSE
Dynamic: author
Dynamic: author-email
Dynamic: classifier
Dynamic: description
Dynamic: description-content-type
Dynamic: home-page
Dynamic: license-file
Dynamic: requires-python
Dynamic: summary
